[
    {
        "üst giyim": [
            "top",
            "bra",
            "pareo"
        ],
        "çanta": [
            "torba"
        ],
        "aksesuar": [
            [
                "kravat",
                "tie"
            ],
            [
                "boyunluk",
                "Neck Wrap"
            ],
            [
                "mendil",
                "handkerchief"
            ]
        ],
        "iç giyim": [
            "teddy"
        ],
        "atkı": [
            "fular"
        ],
        "alt giyim": [
            [
                "tayt",
                "legging"
            ]
        ],
        "Kolleksiyonlar": [
            [
                "kış",
                "winter"
            ]
        ]
    }
]